<?xml version="1.0" encoding="UTF-8"?>
<SURVEYS>

<SURVEY>
  <ID>179001</ID>
  <STAGES>7</STAGES>
  <CLIENT>TABLE HIDE</CLIENT>
  <SUBJECT>test, MULTI TABLE HIDE</SUBJECT>
  <FIRST_NUMBER>1</FIRST_NUMBER>
  <LAST_NUMBER>20000</LAST_NUMBER>
  <INTV_NUMBER>TABLE HIDE</INTV_NUMBER>
  <USER_ID>gosc%</USER_ID>
  <USER_ID>guest%</USER_ID>
  <USER_ID>Zbyszek%21</USER_ID>
  <USER_ID>Ania%22</USER_ID>
  <USER_ID>xyz1%</USER_ID>
  <USER_ID>xyz2%</USER_ID>
  <USER_ID>xyz3%</USER_ID>
  <USER_ID>xyz4%</USER_ID>
  <USER_ID>xyz5%</USER_ID>
  <USER_ID>xyz6%</USER_ID>
  <USER_ID>xyz7%</USER_ID>
  <USER_ID>xyz8%</USER_ID>
  <USER_ID>xyz9%</USER_ID>
  <USER_ID>xyz10%</USER_ID>
  <USER_ID>xyz11%</USER_ID>
  <USER_ID>xyz12%</USER_ID>
  <USER_ID>xyz13%</USER_ID>
  <USER_ID>xyz14%</USER_ID>
  <USER_ID>xyz15%</USER_ID>
  <USER_ID>xyz16%</USER_ID>
  <USER_ID>xyz17%</USER_ID>
  <USER_ID>xyz18%</USER_ID>
  <USER_ID>xyz19%</USER_ID>
  <USER_ID>xyz20%</USER_ID>
  <USER_ID>xyz21%</USER_ID>
  <USER_ID>xyz22%</USER_ID>
  <USER_ID>xyz23%</USER_ID>
  <USER_ID>xyz24%</USER_ID>
  <USER_ID>xyz25%</USER_ID>
  <USER_ID>xyz26%</USER_ID>
  <USER_ID>xyz27%</USER_ID>
  <USER_ID>xyz28%</USER_ID>
  <USER_ID>xyz29%</USER_ID>
  <USER_ID>xyz30%</USER_ID>
  <USER_ID>xyz31%</USER_ID>
  <USER_ID>xyz32%</USER_ID>
  <USER_ID>xyz33%</USER_ID>
  <USER_ID>xyz34%</USER_ID>
  <USER_ID>xyz35%</USER_ID>
  <USER_ID>xyz36%</USER_ID>
  <USER_ID>xyz37%</USER_ID>
  <USER_ID>xyz38%</USER_ID>
  <USER_ID>xyz39%</USER_ID>
  <USER_ID>xyz40%</USER_ID>
  <USER_ID>xyz41%</USER_ID>
  <USER_ID>xyz42%</USER_ID>
  <USER_ID>xyz43%</USER_ID>
  <USER_ID>xyz44%</USER_ID>
  <USER_ID>xyz45%</USER_ID>
  <USER_ID>xyz46%</USER_ID>
  <USER_ID>xyz47%</USER_ID>
  <USER_ID>xyz48%</USER_ID>
  <USER_ID>xyz49%</USER_ID>
  <USER_ID>xyz50%</USER_ID>
  <USER_ID>xyz51%</USER_ID>
  <USER_ID>xyz52%</USER_ID>
  <USER_ID>xyz53%</USER_ID>
  <USER_ID>xyz54%</USER_ID>
  <USER_ID>xyz55%</USER_ID>
  <USER_ID>xyz56%</USER_ID>
  <USER_ID>xyz57%</USER_ID>
  <USER_ID>xyz58%</USER_ID>
  <USER_ID>xyz59%</USER_ID>
  <USER_ID>xyz60%</USER_ID>
  <USER_ID>xyz61%</USER_ID>
  <USER_ID>xyz62%</USER_ID>
  <USER_ID>xyz63%</USER_ID>
  <USER_ID>xyz64%</USER_ID>
  <USER_ID>xyz65%</USER_ID>
  <USER_ID>xyz66%</USER_ID>
  <USER_ID>xyz67%</USER_ID>
  <USER_ID>xyz68%</USER_ID>
  <USER_ID>xyz69%</USER_ID>
  <USER_ID>xyz70%</USER_ID>
  <USER_ID>xyz71%</USER_ID>
  <USER_ID>xyz72%</USER_ID>
  <USER_ID>xyz73%</USER_ID>
  <USER_ID>xyz74%</USER_ID>
  <USER_ID>xyz75%</USER_ID>
  <USER_ID>xyz76%</USER_ID>
  <USER_ID>xyz77%</USER_ID>
  <USER_ID>xyz78%</USER_ID>
  <USER_ID>xyz79%</USER_ID>
  <USER_ID>xyz80%</USER_ID>
  <USER_ID>xyz81%</USER_ID>
  <USER_ID>xyz82%</USER_ID>
  <USER_ID>xyz83%</USER_ID>
  <USER_ID>xyz84%</USER_ID>
  <USER_ID>xyz85%</USER_ID>
  <USER_ID>xyz86%</USER_ID>
  <USER_ID>xyz87%</USER_ID>
  <USER_ID>xyz88%</USER_ID>
  <USER_ID>xyz89%</USER_ID>
  <USER_ID>xyz90%</USER_ID>
  <USER_ID>xyz91%</USER_ID>
  <USER_ID>xyz92%</USER_ID>
  <USER_ID>xyz93%</USER_ID>
  <USER_ID>xyz94%</USER_ID>
  <USER_ID>xyz95%</USER_ID>
  <USER_ID>xyz96%</USER_ID>
  <USER_ID>xyz97%</USER_ID>
  <USER_ID>xyz98%</USER_ID>
  <USER_ID>xyz99%</USER_ID>
  <USER_ID>xyz100%</USER_ID>
  <USER_ID>xyz101%</USER_ID>
  <USER_ID>xyz102%</USER_ID>
  <USER_ID>xyz103%</USER_ID>
  <USER_ID>xyz104%</USER_ID>
  <USER_ID>xyz105%</USER_ID>
  <USER_ID>xyz106%</USER_ID>
  <USER_ID>xyz107%</USER_ID>
  <USER_ID>xyz108%</USER_ID>
  <USER_ID>xyz109%</USER_ID>
  <USER_ID>xyz110%</USER_ID>
  <USER_ID>xyz111%</USER_ID>
  <USER_ID>xyz112%</USER_ID>
  <USER_ID>xyz113%</USER_ID>
  <USER_ID>xyz114%</USER_ID>
  <USER_ID>xyz115%</USER_ID>
  <USER_ID>xyz116%</USER_ID>
  <USER_ID>xyz117%</USER_ID>
  <USER_ID>xyz118%</USER_ID>
  <USER_ID>xyz119%</USER_ID>
  <USER_ID>xyz120%</USER_ID>
  <USER_ID>xyz121%</USER_ID>
  <USER_ID>xyz122%</USER_ID>
  <USER_ID>xyz123%</USER_ID>
  <USER_ID>xyz124%</USER_ID>
  <USER_ID>xyz125%</USER_ID>
  <USER_ID>xyz126%</USER_ID>
  <USER_ID>xyz127%</USER_ID>
  <USER_ID>xyz128%</USER_ID>
  <USER_ID>xyz129%</USER_ID>
  <USER_ID>xyz130%</USER_ID>
  <USER_ID>xyz131%</USER_ID>
  <USER_ID>xyz132%</USER_ID>
  <USER_ID>xyz133%</USER_ID>
  <USER_ID>xyz134%</USER_ID>
  <USER_ID>xyz135%</USER_ID>
  <USER_ID>xyz136%</USER_ID>
  <USER_ID>xyz137%</USER_ID>
  <USER_ID>xyz138%</USER_ID>
  <USER_ID>xyz139%</USER_ID>
  <USER_ID>xyz140%</USER_ID>
  <USER_ID>xyz141%</USER_ID>
  <USER_ID>xyz142%</USER_ID>
  <USER_ID>xyz143%</USER_ID>
  <USER_ID>xyz144%</USER_ID>
  <USER_ID>xyz145%</USER_ID>
  <USER_ID>xyz146%</USER_ID>
  <USER_ID>xyz147%</USER_ID>
  <USER_ID>xyz148%</USER_ID>
  <USER_ID>xyz149%</USER_ID>
  <USER_ID>xyz150%</USER_ID>
  <USER_ID>xyz151%</USER_ID>
  <USER_ID>xyz152%</USER_ID>
  <USER_ID>xyz153%</USER_ID>
  <USER_ID>xyz154%</USER_ID>
  <USER_ID>xyz155%</USER_ID>
  <USER_ID>xyz156%</USER_ID>
  <USER_ID>xyz157%</USER_ID>
  <USER_ID>xyz158%</USER_ID>
  <USER_ID>xyz159%</USER_ID>
  <USER_ID>xyz160%</USER_ID>
  <USER_ID>xyz161%</USER_ID>
  <USER_ID>xyz162%</USER_ID>
  <USER_ID>xyz163%</USER_ID>
  <USER_ID>xyz164%</USER_ID>
  <USER_ID>xyz165%</USER_ID>
  <USER_ID>xyz166%</USER_ID>
  <USER_ID>xyz167%</USER_ID>
  <USER_ID>xyz168%</USER_ID>
  <USER_ID>xyz169%</USER_ID>
  <USER_ID>xyz170%</USER_ID>
  <USER_ID>xyz171%</USER_ID>
  <USER_ID>xyz172%</USER_ID>
  <USER_ID>xyz173%</USER_ID>
  <USER_ID>xyz174%</USER_ID>
  <USER_ID>xyz175%</USER_ID>
  <USER_ID>xyz176%</USER_ID>
  <USER_ID>xyz177%</USER_ID>
  <USER_ID>xyz178%</USER_ID>
  <USER_ID>xyz179%</USER_ID>
  <USER_ID>xyz180%</USER_ID>
  <USER_ID>xyz181%</USER_ID>
  <USER_ID>xyz182%</USER_ID>
  <USER_ID>xyz183%</USER_ID>
  <USER_ID>xyz184%</USER_ID>
  <USER_ID>xyz185%</USER_ID>
  <USER_ID>xyz186%</USER_ID>
  <USER_ID>xyz187%</USER_ID>
  <USER_ID>xyz188%</USER_ID>
  <USER_ID>xyz189%</USER_ID>
  <USER_ID>xyz190%</USER_ID>
  <USER_ID>xyz191%</USER_ID>
  <USER_ID>xyz192%</USER_ID>
  <USER_ID>xyz193%</USER_ID>
  <USER_ID>xyz194%</USER_ID>
  <USER_ID>xyz195%</USER_ID>
  <USER_ID>xyz196%</USER_ID>
  <USER_ID>xyz197%</USER_ID>
  <USER_ID>xyz198%</USER_ID>
  <USER_ID>xyz199%</USER_ID>
  <USER_ID>xyz200%</USER_ID>
</SURVEY>

</SURVEYS>